[
  {
    "type": "effect_on_condition",
    "id": "EOC_FRS_ACTIVATE",
    "effect": [
      {
        "u_add_effect": "fungal_reality_shift_active",
        "duration": "24 hours"
      },
      {
        "u_message": "You feel the world around you begin to shift and change..."
      }
    ]
  },
  {
    "type": "effect_on_condition",
    "id": "EOC_FRS_CHECK_ACTIVE",
    "recurrence": "1 minutes",
    "global": true,
    "condition": {
      "and": [
        {
          "u_has_effect": "fungal_reality_shift_active"
        }
      ]
    },
    "effect": [
      {
        "run_eocs": "EOC_FRS_TRANSFORM_TERRAIN"
      },
      {
        "u_message": "The world around you shifts and changes...",
        "type": "debug"
      }
    ]
  },
  {
    "type": "effect_on_condition",
    "id": "EOC_FRS_TRANSFORM_TERRAIN",
    "effect": [
      {
        "u_location_variable": { "u_val": "transform_center" },
        "min_radius": 0,
        "max_radius": 0
      },
      {
        "weighted_list_eocs": [
          [ "EOC_FRS_TRANSFORM_LIQUID_DYNAMIC", 1 ],
          [ "EOC_FRS_TRANSFORM_WALL_DYNAMIC", 1 ]
        ]
      }
    ]
  }
]